{
    "Peak Memory KB": 389412,
    "RunTime": 1148.145886958,
    "tests": [
        {
            "results": [
                {
                    "avgCorrectNodeDelivered": 49.49,
                    "avgDeliveryRound": 7.979591836734694,
                    "avgMessagesSent": 35515.03,
                    "totalMessagesSent": 3515988
                }
            ]
        },
        {
            "results": [
                {
                    "avgCorrectNodeDelivered": 49.49,
                    "avgDeliveryRound": 10.387755102040817,
                    "avgMessagesSent": 34937.2,
                    "totalMessagesSent": 3458783
                }
            ]
        },
        {
            "results": [
                {
                    "avgCorrectNodeDelivered": 49.49,
                    "avgDeliveryRound": 27.183673469387756,
                    "avgMessagesSent": 35382.36,
                    "totalMessagesSent": 3502854
                }
            ]
        },
        {
            "results": [
                {
                    "avgCorrectNodeDelivered": 49.49,
                    "avgDeliveryRound": 7.571428571428571,
                    "avgMessagesSent": 35952.26,
                    "totalMessagesSent": 3559274
                }
            ]
        },
        {
            "results": [
                {
                    "avgCorrectNodeDelivered": 49.49,
                    "avgDeliveryRound": 7.0,
                    "avgMessagesSent": 35987.02,
                    "totalMessagesSent": 3562715
                }
            ]
        },
        {
            "results": [
                {
                    "avgCorrectNodeDelivered": 49.49,
                    "avgDeliveryRound": 8.428571428571429,
                    "avgMessagesSent": 36022.26,
                    "totalMessagesSent": 3566204
                }
            ]
        },
        {
            "results": [
                {
                    "avgCorrectNodeDelivered": 49.49,
                    "avgDeliveryRound": 7.795918367346939,
                    "avgMessagesSent": 35415.72,
                    "totalMessagesSent": 3506156
                }
            ]
        },
        {
            "results": [
                {
                    "avgCorrectNodeDelivered": 49.49,
                    "avgDeliveryRound": 9.142857142857142,
                    "avgMessagesSent": 35547.98,
                    "totalMessagesSent": 3519250
                }
            ]
        },
        {
            "results": [
                {
                    "avgCorrectNodeDelivered": 49.49,
                    "avgDeliveryRound": 6.061224489795919,
                    "avgMessagesSent": 35193.39,
                    "totalMessagesSent": 3484146
                }
            ]
        },
        {
            "results": [
                {
                    "avgCorrectNodeDelivered": 49.49,
                    "avgDeliveryRound": 10.224489795918368,
                    "avgMessagesSent": 36338.2,
                    "totalMessagesSent": 3597482
                }
            ]
        }
    ]
}
