{
    "Peak Memory KB": 267556,
    "RunTime": 1208.281519327,
    "tests": [
        {
            "results": [
                {
                    "avgCorrectNodeDelivered": 50.54,
                    "avgDeliveryRound": 6.808510638297872,
                    "avgMessagesSent": 27074.44,
                    "totalMessagesSent": 2517923
                }
            ]
        },
        {
            "results": [
                {
                    "avgCorrectNodeDelivered": 50.54,
                    "avgDeliveryRound": 7.957446808510638,
                    "avgMessagesSent": 27133.02,
                    "totalMessagesSent": 2523371
                }
            ]
        },
        {
            "results": [
                {
                    "avgCorrectNodeDelivered": 50.54,
                    "avgDeliveryRound": 4.914893617021277,
                    "avgMessagesSent": 27237.13,
                    "totalMessagesSent": 2533053
                }
            ]
        },
        {
            "results": [
                {
                    "avgCorrectNodeDelivered": 50.54,
                    "avgDeliveryRound": 6.702127659574468,
                    "avgMessagesSent": 27066.91,
                    "totalMessagesSent": 2517223
                }
            ]
        },
        {
            "results": [
                {
                    "avgCorrectNodeDelivered": 50.54,
                    "avgDeliveryRound": 8.27659574468085,
                    "avgMessagesSent": 27128.29,
                    "totalMessagesSent": 2522931
                }
            ]
        },
        {
            "results": [
                {
                    "avgCorrectNodeDelivered": 50.54,
                    "avgDeliveryRound": 7.574468085106383,
                    "avgMessagesSent": 27036.81,
                    "totalMessagesSent": 2514423
                }
            ]
        },
        {
            "results": [
                {
                    "avgCorrectNodeDelivered": 50.54,
                    "avgDeliveryRound": 6.042553191489362,
                    "avgMessagesSent": 27203.59,
                    "totalMessagesSent": 2529934
                }
            ]
        },
        {
            "results": [
                {
                    "avgCorrectNodeDelivered": 50.54,
                    "avgDeliveryRound": 8.02127659574468,
                    "avgMessagesSent": 26975.23,
                    "totalMessagesSent": 2508696
                }
            ]
        },
        {
            "results": [
                {
                    "avgCorrectNodeDelivered": 50.54,
                    "avgDeliveryRound": 5.787234042553192,
                    "avgMessagesSent": 27004.4,
                    "totalMessagesSent": 2511409
                }
            ]
        },
        {
            "results": [
                {
                    "avgCorrectNodeDelivered": 50.54,
                    "avgDeliveryRound": 6.574468085106383,
                    "avgMessagesSent": 26925.51,
                    "totalMessagesSent": 2504072
                }
            ]
        }
    ]
}
